LICENSE
MANIFEST.in
NOTICE
README.rst
setup.py
django_litetest/__init__.py
django_litetest/manage.py
django_litetest.egg-info/PKG-INFO
django_litetest.egg-info/SOURCES.txt
django_litetest.egg-info/dependency_links.txt
django_litetest.egg-info/requires.txt
django_litetest.egg-info/top_level.txt
django_litetest.egg-info/zip-safe
django_litetest/management/__init__.py
django_litetest/management/commands/__init__.py
django_litetest/management/commands/litetest.py