Metadata-Version: 1.1
Name: django-litetest
Version: 1.0
Summary: A lightweight Django "test" command for quick unittest runs.
Home-page: https://github.com/sfllaw/django-litetest
Author: Simon Law
Author-email: sfllaw@sfllaw.ca
License: Apache Software License, version 2.0
Platform: UNKNOWN
Classifier: Development Status :: 5 - Production/Stable
Classifier: Environment :: Web Environment
Classifier: Framework :: Django
Classifier: Intended Audience :: Developers
Classifier: License :: OSI Approved :: Apache Software License
Classifier: Operating System :: OS Independent
Classifier: Programming Language :: Python
Classifier: Programming Language :: Python :: 2.6
Classifier: Programming Language :: Python :: 2.7
Classifier: Topic :: Software Development :: Libraries
